<?xml version="1.0" encoding="UTF-8"?>
<AMLWatchList xmlns="http://www.huawei.com/cps/aml/extract/operator" xmlns:xsi="http://www.w3.org/2001/XMLSchema-instance" xsi:schemaLocation="http://www.huawei.com/cps/aml/extract/operator OperatorExtract.xsd ">
<Header>Source:MM; Sequence NO,Task Type:3,operator; Date Time:2019-06-20 14:11:33</Header>
<Operators>
</Operators>
<Footer>Number of Records:0</Footer>
<Checksum>C2DE6AE692B9D167580AF552F574897E0440073B4888EBCC3E2963DE1A915704</Checksum>
</AMLWatchList>