<?xml version="1.0" encoding="UTF-8"?>
<AMLWatchList xmlns="http://www.huawei.com/cps/aml/extract/operator" xmlns:xsi="http://www.w3.org/2001/XMLSchema-instance" xsi:schemaLocation="http://www.huawei.com/cps/aml/extract/operator OperatorExtract.xsd ">
<Header>Source:MM; Sequence NO,Task Type:1,operator; Date Time:2019-06-29 22:00:01</Header>
<Operators>
</Operators>
<Footer>Number of Records:0</Footer>
<Checksum>D7C072E82107300B5BDE6DCE0C22824B04874F837B8CE8ACE34C65987C660135</Checksum>
</AMLWatchList>