<?xml version="1.0" encoding="UTF-8"?>
<AMLWatchList xmlns="http://www.huawei.com/cps/aml/extract/operator" xmlns:xsi="http://www.w3.org/2001/XMLSchema-instance" xsi:schemaLocation="http://www.huawei.com/cps/aml/extract/operator OperatorExtract.xsd ">
<Header>Source:MM; Sequence NO,Task Type:8,operator; Date Time:2019-06-20 14:32:48</Header>
<Operators>
</Operators>
<Footer>Number of Records:0</Footer>
<Checksum>464F7E0FB57D62175CC5EC1ED27E027F2AE8A40E65DBAB02C2AED3E9174B21DA</Checksum>
</AMLWatchList>